dqp/__init__.py
dqp/apps.py
dqp/constants.py
dqp/decorators.py
dqp/exceptions.py
dqp/manager.py
dqp/prepared_stmt.py
dqp/prepared_stmt_controller.py
dqp/query.py
dqp/queryset.py
dqp/sql_compiler.py
dqp/testing.py
django_query_preparer-1.0.1.dist-info/LICENCE.txt
django_query_preparer-1.0.1.dist-info/METADATA
django_query_preparer-1.0.1.dist-info/WHEEL
django_query_preparer-1.0.1.dist-info/top_level.txt
django_query_preparer-1.0.1.dist-info/RECORD
