Metadata-Version: 2.1
Name: django-query-preparer
Version: 1.0.1
Summary: A package to prepare queries in postgres before execution
Home-page: https://github.com/vercer-cmt/django-query-preparer
Author: Dan Greenhalgh
Author-email: dgreenhalgh@vercer.co.uk
License: UNKNOWN
Platform: UNKNOWN
Classifier: Programming Language :: Python :: 3
Classifier: Framework :: Django
Classifier: License :: OSI Approved :: MIT License
Classifier: Operating System :: OS Independent
Requires-Python: >=3.6
